libgenesis/__init__.py
libgenesis/download.py
libgenesis/search.py
libgenesis/utils.py
tests/__init__.py
tests/libgen_test.py
libgenesis-0.1.9.dist-info/LICENSE
libgenesis-0.1.9.dist-info/METADATA
libgenesis-0.1.9.dist-info/WHEEL
libgenesis-0.1.9.dist-info/top_level.txt
libgenesis-0.1.9.dist-info/RECORD
