Metadata-Version: 2.1
Name: libgenesis
Version: 0.1.9
Summary: Asynchronous python lib for Libgen.rs
Home-page: https://github.com/Samfun75/libgenesis
Download-URL: https://github.com/Samfun75/libgenesis/archive/v0.1.9.tar.gz
Author: Samson Misganaw
Author-email: samfunn75@gmail.com
License: MIT License
Platform: UNKNOWN
Classifier: Intended Audience :: Developers
Classifier: Operating System :: OS Independent
Classifier: Programming Language :: Python
Classifier: Programming Language :: Python :: 3.8
Classifier: Programming Language :: Python :: 3.9
Classifier: Topic :: Internet :: WWW/HTTP
License-File: LICENSE
Requires-Dist: aiofiles (>=0.5.0)
Requires-Dist: aiohttp (>=3.6.0)
Requires-Dist: beautifulsoup4 (>=4.9.0)
Requires-Dist: lxml (>=4.6.5)
Requires-Dist: requests (>=2.25.0)
Requires-Dist: tldextract (>=3.1.0)
